deforce/__init__.py
deforce/model/__init__.py
deforce/model/base_cfn_numpy.py
deforce/model/base_cfn_torch.py
deforce/model/dfo_cfn.py
deforce/model/dfo_tune_cfn.py
deforce/model/gd_cfn.py
deforce/toolkit/__init__.py
deforce/toolkit/activators.py
deforce/toolkit/metrics.py
deforce/toolkit/preprocessor.py
deforce/toolkit/scalers.py
deforce/toolkit/validators.py
deforce-1.0.0.dist-info/LICENSE
deforce-1.0.0.dist-info/METADATA
deforce-1.0.0.dist-info/WHEEL
deforce-1.0.0.dist-info/top_level.txt
deforce-1.0.0.dist-info/RECORD
